larry/__init__.py
larry/entrypoint.py
larry/web.py
larry/www/asset-manifest.json
larry/www/index.html
larry/www/larry.avif
larry/www/static/css/main.05d97a40.css
larry/www/static/css/main.05d97a40.css.map
larry/www/static/js/main.ce6f419e.js
larry/www/static/js/main.ce6f419e.js.LICENSE.txt
larry/www/static/js/main.ce6f419e.js.map
larry_ai-0.0.1.dist-info/METADATA
larry_ai-0.0.1.dist-info/WHEEL
larry_ai-0.0.1.dist-info/entry_points.txt
larry_ai-0.0.1.dist-info/top_level.txt
larry_ai-0.0.1.dist-info/RECORD
